{
  "_class": "symbolInstance",
  "do_objectID": "6D913BCC-8251-432A-92D6-6C9E119BE2EF",
  "exportOptions": {
    "_class": "exportOptions",
    "exportFormats": [
    ],
    "includedLayerIds": [
    ],
    "layerOptions": 0,
    "shouldTrim": false
  },
  "frame": {
    "_class": "rect",
    "constrainProportions": false,
    "height": 250,
    "width": 400,
    "x": 58,
    "y": 340
  },
  "horizontalSpacing": 0,
  "isFlippedHorizontal": false,
  "isFlippedVertical": false,
  "isLocked": false,
  "isVisible": true,
  "layerListExpandedType": 0,
  "masterInfluenceEdgeMaxXPadding": 0,
  "masterInfluenceEdgeMaxYPadding": 1,
  "masterInfluenceEdgeMinXPadding": 0,
  "masterInfluenceEdgeMinYPadding": 0,
  "name": "chelsea-lg",
  "nameIsFixed": false,
  "originalObjectID": "56BE9B09-C8E3-4720-840E-D318790A29A0",
  "resizingConstraint": 63,
  "resizingType": 0,
  "rotation": 0,
  "shouldBreakMaskChain": false,
  "style": {
    "_class": "style",
    "endDecorationType": 0,
    "miterLimit": 10,
    "shadows": [
      {
        "_class": "shadow",
        "blurRadius": 4,
        "color": {
          "_class": "color",
          "alpha": 0.5,
          "blue": 0,
          "green": 0,
          "red": 0
        },
        "contextSettings": {
          "_class": "graphicsContextSettings",
          "blendMode": 0,
          "opacity": 1
        },
        "isEnabled": true,
        "offsetX": 0,
        "offsetY": 2,
        "spread": 0
      }
    ],
    "startDecorationType": 0
  },
  "symbolID": "4DDD03E2-C9C4-4539-9249-22D2F7951DA8",
  "userInfo": {
    "com.animaapp.stc-sketch-plugin": {
      "kModelPropertiesKey": {
      }
    }
  },
  "verticalSpacing": 0
}