{
  "_class": "bitmap",
  "clippingMask": "{{0, 0}, {1, 1}}",
  "do_objectID": "EA6AC00F-0D70-4DE8-8D4C-19EBF03766B6",
  "exportOptions": {
    "_class": "exportOptions",
    "exportFormats": [
    ],
    "includedLayerIds": [
    ],
    "layerOptions": 0,
    "shouldTrim": false
  },
  "fillReplacesImage": false,
  "frame": {
    "_class": "rect",
    "constrainProportions": true,
    "height": 569,
    "width": 1440,
    "x": 0,
    "y": 1329
  },
  "image": {
    "_class": "MSJSONFileReference",
    "_ref": "images/8ecfaf0e8c168fb860d49fabe0fca0047900b0a8",
    "_ref_class": "MSImageData"
  },
  "isFlippedHorizontal": false,
  "isFlippedVertical": false,
  "isLocked": false,
  "isVisible": true,
  "layerListExpandedType": 0,
  "name": "new-standard-hero",
  "nameIsFixed": false,
  "nineSliceCenterRect": "{{0, 0}, {0, 0}}",
  "nineSliceScale": "{0, 0}",
  "resizingConstraint": 63,
  "resizingType": 0,
  "rotation": 0,
  "shouldBreakMaskChain": false,
  "style": {
    "_class": "style",
    "endDecorationType": 0,
    "miterLimit": 10,
    "startDecorationType": 0
  },
  "userInfo": {
    "com.animaapp.stc-sketch-plugin": {
      "kModelPropertiesKey": {
        "constraints": {
          "aspectRatio": {
            "constant": 569,
            "enabled": 1,
            "modelID": "constraint_12c52ac6-e2b9-47c5-8b69-139210f4b5e6",
            "model_class": "ADModelConstraint",
            "model_version": 0.1,
            "multiplier": 1440
          },
          "automatic": 1,
          "modelID": "viewConstraints_c12b214b-4edb-423c-a92f-c519f08f1b4d",
          "model_class": "ADModelViewConstraints",
          "model_version": 0.1,
          "scaleFactor": 1
        }
      }
    }
  }
}