{
  "_class": "bitmap",
  "clippingMask": "{{0, 0}, {1, 1}}",
  "do_objectID": "4FC2A92F-00C6-4E84-B9F1-442EF2AB7112",
  "exportOptions": {
    "_class": "exportOptions",
    "exportFormats": [
    ],
    "includedLayerIds": [
    ],
    "layerOptions": 0,
    "shouldTrim": false
  },
  "fillReplacesImage": false,
  "frame": {
    "_class": "rect",
    "constrainProportions": true,
    "height": 297,
    "width": 297,
    "x": 171,
    "y": 132
  },
  "image": {
    "_class": "MSJSONFileReference",
    "_ref": "images/02a191d48c445c347e8ce5f7af5ae9f5ee3c0b46",
    "_ref_class": "MSImageData"
  },
  "isFlippedHorizontal": false,
  "isFlippedVertical": false,
  "isLocked": false,
  "isVisible": true,
  "layerListExpandedType": 0,
  "name": "Genevievex2-1",
  "nameIsFixed": false,
  "nineSliceCenterRect": "{{0, 0}, {0, 0}}",
  "nineSliceScale": "{0, 0}",
  "resizingConstraint": 63,
  "resizingType": 0,
  "rotation": 0,
  "shouldBreakMaskChain": false,
  "style": {
    "_class": "style",
    "borders": [
      {
        "_class": "border",
        "color": {
          "_class": "color",
          "alpha": 1,
          "blue": 0.5137254901960783,
          "green": 0.7647058823529411,
          "red": 0.8862745098039215
        },
        "fillType": 0,
        "isEnabled": true,
        "position": 2,
        "thickness": 2
      }
    ],
    "endDecorationType": 0,
    "miterLimit": 10,
    "startDecorationType": 0
  }
}